counter_4bit.v
module counter_4bit (
  input clk,
  input rst_n,      // active-low reset
  output reg [3:0] q
);

always @(posedge clk or negedge rst_n) begin
  if (!rst_n)
    q <= 4'b0000;   // Reset counter to 0
  else
    q <= q + 1;     // Increment counter
end

endmodule

counter_4bit_tb.v
module counter_4bit_tb;

reg clk;
reg rst_n;
wire [3:0] q;

// Instantiate DUT (Device Under Test)
counter_4bit uut (
  .clk(clk),
  .rst_n(rst_n),
  .q(q)
);

// Clock generation: toggle every 5 time units (period = 10)
always begin
  clk = 0; #5;
  clk = 1; #5;
end

initial begin
  $monitor("Time=%0t | rst_n=%b | q=%b", $time, rst_n, q);

  // Initial conditions
  rst_n = 0; #12;    // Assert reset for a bit
  rst_n = 1;         // Release reset

  #100;              // Let it run for a while

  rst_n = 0; #10;    // Apply reset again
  rst_n = 1;         // Release reset

  #50;               // Run more

  $finish;
end

// For waveform
initial begin
  $dumpfile("counter_4bit.vcd");
  $dumpvars(0, counter_4bit_tb);
end

endmodule

counter_4bit.vcd
$date
	Sat Jun 28 20:52:44 2025
$end
$version
	Icarus Verilog
$end
$timescale
	1s
$end
$scope module counter_4bit_tb $end
$var wire 4 ! q [3:0] $end
$var reg 1 " clk $end
$var reg 1 # rst_n $end
$scope module uut $end
$var wire 1 " clk $end
$var wire 1 # rst_n $end
$var reg 4 $ q [3:0] $end
$upscope $end
$upscope $end
$enddefinitions $end
$comment Show the parameter values. $end
$dumpall
$end
#0
$dumpvars
b0 $
0#
0"
b0 !
$end
#5
1"
#10
0"
#12
1#
#15
b1 !
b1 $
1"
#20
0"
#25
b10 !
b10 $
1"
#30
0"
#35
b11 !
b11 $
1"
#40
0"
#45
b100 !
b100 $
1"
#50
0"
#55
b101 !
b101 $
1"
#60
0"
#65
b110 !
b110 $
1"
#70
0"
#75
b111 !
b111 $
1"
#80
0"
#85
b1000 !
b1000 $
1"
#90
0"
#95
b1001 !
b1001 $
1"
#100
0"
#105
b1010 !
b1010 $
1"
#110
0"
#112
b0 !
b0 $
0#
#115
1"
#120
0"
#122
1#
#125
b1 !
b1 $
1"
#130
0"
#135
b10 !
b10 $
1"
#140
0"
#145
b11 !
b11 $
1"
#150
0"
#155
b100 !
b100 $
1"
#160
0"
#165
b101 !
b101 $
1"
